citellus-1.5.0.20210503144234.data/scripts/citellus.py
citellus-1.5.0.20210503144234.data/scripts/magui.py
citellusclient/__init__.py
citellusclient/citellus.html
citellusclient/citellus.sh
citellusclient/common-functions.sh
citellusclient/magui.py
citellusclient/shell.py
citellusclient/common.d/00-core.sh
citellusclient/common.d/01-date.sh
citellusclient/common.d/01-dpkg.sh
citellusclient/common.d/01-rpm.sh
citellusclient/common.d/01-virt.sh
citellusclient/common.d/02-pkg.sh
citellusclient/common.d/10-openshift.sh
citellusclient/common.d/10-openstack.sh
citellusclient/common.d/20-container.sh
citellusclient/extensions/.placeholder
citellusclient/extensions/__init__.py
citellusclient/extensions/ansible.py
citellusclient/extensions/core.py
citellusclient/extensions/faraday-exec.py
citellusclient/extensions/faraday.py
citellusclient/extensions/golang.py
citellusclient/extensions/metadata.py
citellusclient/extensions/nagios.py
citellusclient/extensions/node-problem-detector.py
citellusclient/extensions/rhv-log-collector-analyzer.py
citellusclient/extensions/tripleo-common-healthcheck.py
citellusclient/extensions/winston.py
citellusclient/hooks/data/0/faraday-exec/merge-with-faraday.py
citellusclient/hooks/data/0/insights-core-unifier-merge-loader/insights-json.py
citellusclient/hooks/data/0/network/move-global-mtu-to-individual-faraday-positive.py
citellusclient/hooks/data/0/system/move-global-multipath-to-individual-faraday-positive.py
citellusclient/hooks/data/9/faraday-to-individual.py
citellusclient/hooks/data/9/rhv-log-collector-analyzer-to-individual.py
citellusclient/hooks/data/9/system/unfail-chronyd-with-ntpd.py
citellusclient/hooks/data/9/system/unfail-firewall-with-openstack.py
citellusclient/hooks/data/9/system/unfail-ntpd-with-chronyd.py
citellusclient/hooks/profiles/profiles.py
citellusclient/locale/en/LC_MESSAGES/.placeholder
citellusclient/plugins/ansible/.placeholder
citellusclient/plugins/ansible/openstack/rabbitmq/ha-policies.yml
citellus-1.5.0.20210503144234.dist-info/AUTHORS
citellus-1.5.0.20210503144234.dist-info/LICENSE
citellus-1.5.0.20210503144234.dist-info/METADATA
citellus-1.5.0.20210503144234.dist-info/WHEEL
citellus-1.5.0.20210503144234.dist-info/pbr.json
citellus-1.5.0.20210503144234.dist-info/top_level.txt
citellus-1.5.0.20210503144234.dist-info/RECORD
